promclient_to_openapi/__init__.py
promclient_to_openapi/packages.py
promclient_to_openapi/py.typed
promclient_to_openapi/synchronous.py
promclient_to_openapi/utils.py
promclient_to_openapi/fastapi/__init__.py
promclient_to_openapi/fastapi/models.py
promclient_to_openapi/fastapi/openapi.py
promclient_to_openapi-1.1.1.dist-info/licenses/LICENSE
promclient_to_openapi-1.1.1.dist-info/METADATA
promclient_to_openapi-1.1.1.dist-info/WHEEL
promclient_to_openapi-1.1.1.dist-info/top_level.txt
promclient_to_openapi-1.1.1.dist-info/RECORD
