Metadata-Version: 2.4
Name: promclient_to_openapi
Version: 1.1.1
Summary: Translates prometheus_client metrics into OpenAPI specification.
Author-email: Alexander Pozlevich <apozlevich@gmail.com>
Classifier: Development Status :: 3 - Alpha
Classifier: Topic :: System :: Monitoring
Classifier: Programming Language :: Python :: 3 :: Only
Classifier: Programming Language :: Python :: 3.13
Classifier: Typing :: Typed
Requires-Python: >=3.13
License-File: LICENSE
Requires-Dist: fastapi>=0.121.0
Requires-Dist: prometheus-client>=0.22.1
Provides-Extra: dev
Requires-Dist: pytest; extra == "dev"
Requires-Dist: ruff; extra == "dev"
Dynamic: license-file
